airthings/__init__.py
airthings/constants.py
airthings/exceptions.py
airthings/models.py
airthings/utils.py
airthings/devices/__init__.py
airthings/devices/utils.py
airthings/devices/wave_gen_1.py
airthings/devices/wave_gen_2.py
airthings/devices/wave_mini_gen_1.py
airthings/devices/wave_plus_gen_1.py
airthings/sensors/__init__.py
airthings/sensors/atmospheric_pressure.py
airthings/sensors/co2.py
airthings/sensors/humidity.py
airthings/sensors/radon_long_term_average.py
airthings/sensors/radon_short_term_average.py
airthings/sensors/temperature.py
airthings/sensors/voc.py
airthings-3.2.0.dist-info/LICENSE.txt
airthings-3.2.0.dist-info/METADATA
airthings-3.2.0.dist-info/WHEEL
airthings-3.2.0.dist-info/top_level.txt
airthings-3.2.0.dist-info/RECORD
