Metadata-Version: 2.1
Name: airthings
Version: 3.2.0
Summary: Fetch sensor measurements from Airthings devices
Home-page: https://github.com/kotlarz/airthings
Author: Marius Kotlarz
Author-email: marius@kotlarz.no
License: UNKNOWN
Platform: UNKNOWN
Classifier: Development Status :: 4 - Beta
Classifier: Intended Audience :: Developers
Classifier: Intended Audience :: Information Technology
Classifier: License :: OSI Approved :: MIT License
Classifier: Operating System :: POSIX :: Linux
Classifier: Topic :: Home Automation
Classifier: Topic :: Utilities
Requires-Dist: bluepy (==1.3.0)
